{
   "_type":"export",
   "__export_format":4,
   "__export_date":"2022-07-11T21:10:40.642Z",
   "__export_source":"insomnia.desktop.app:v2022.4.2",
   "resources":[
      {
         "_id":"req_108b6d87926b4a1da95a1393d138ce93",
         "parentId":"wrk_4a5a7b0f3f1d40898c0652e42004d10c",
         "modified":1657573750791,
         "created":1643295391265,
         "url":"{{ _.cognito }}",
         "name":"Authenticate config",
         "description":"",
         "method":"POST",
         "body":{
            "mimeType":"application/json",
            "text":"{\n\t\"AuthParameters\": {\n\t\t\"USERNAME\": \"{{ _.config_user_name }}\",\n\t\t\"PASSWORD\": \"{{ _.config_password }}\"\n\t},\n\t\"AuthFlow\": \"USER_PASSWORD_AUTH\",\n\t\"ClientId\": \"{{ _.clientID }}\"\n}"
         },
         "parameters":[
            
         ],
         "headers":[
            {
               "name":"Content-Type",
               "value":"application/x-amz-json-1.1",
               "id":"pair_72dd00b9aecc449191aa3ef0b9b76c02"
            },
            {
               "id":"pair_9e81734bb39f4a94aa142012bbc2c15a",
               "name":"X-Amz-Target",
               "value":"AWSCognitoIdentityProviderService.InitiateAuth",
               "description":""
            }
         ],
         "authentication":{
            
         },
         "metaSortKey":-1643632790175,
         "isPrivate":false,
         "settingStoreCookies":true,
         "settingSendCookies":true,
         "settingDisableRenderRequestBody":false,
         "settingEncodeUrl":true,
         "settingRebuildPath":true,
         "settingFollowRedirects":"global",
         "_type":"request"
      },
      {
         "_id":"wrk_4a5a7b0f3f1d40898c0652e42004d10c",
         "parentId":null,
         "modified":1643293092968,
         "created":1643293092968,
         "name":"Cloud Charging",
         "description":"",
         "scope":"collection",
         "_type":"workspace"
      },
      {
         "_id":"req_76f28bad434041c78a1d8e79c9fc80a8",
         "parentId":"wrk_4a5a7b0f3f1d40898c0652e42004d10c",
         "modified":1657573749734,
         "created":1643624674496,
         "url":"{{ _.cognito }}",
         "name":"Authenticate device",
         "description":"",
         "method":"POST",
         "body":{
            "mimeType":"application/json",
            "text":"{\n\t\"AuthParameters\": {\n\t\t\"USERNAME\": \"{{ _.device_user_name }}\",\n\t\t\"PASSWORD\": \"{{ _.device_password }}\"\n\t},\n\t\"AuthFlow\": \"USER_PASSWORD_AUTH\",\n\t\"ClientId\": \"{{ _.clientID }}\"\n}"
         },
         "parameters":[
            
         ],
         "headers":[
            {
               "name":"Content-Type",
               "value":"application/x-amz-json-1.1",
               "id":"pair_72dd00b9aecc449191aa3ef0b9b76c02"
            },
            {
               "id":"pair_9e81734bb39f4a94aa142012bbc2c15a",
               "name":"X-Amz-Target",
               "value":"AWSCognitoIdentityProviderService.InitiateAuth",
               "description":""
            }
         ],
         "authentication":{
            
         },
         "metaSortKey":-1643632790150,
         "isPrivate":false,
         "settingStoreCookies":true,
         "settingSendCookies":true,
         "settingDisableRenderRequestBody":false,
         "settingEncodeUrl":true,
         "settingRebuildPath":true,
         "settingFollowRedirects":"global",
         "_type":"request"
      },
      {
         "_id":"req_b21810c7581c49cc9dd3791e4ccc1060",
         "parentId":"wrk_4a5a7b0f3f1d40898c0652e42004d10c",
         "modified":1657573749354,
         "created":1643701845111,
         "url":"{{ _.cognito }}",
         "name":"Authenticate infra",
         "description":"",
         "method":"POST",
         "body":{
            "mimeType":"application/json",
            "text":"{\n\t\"AuthParameters\": {\n\t\t\"USERNAME\": \"{{ _.infra_user_name }}\",\n\t\t\"PASSWORD\": \"{{ _.infra_password }}\"\n\t},\n\t\"AuthFlow\": \"USER_PASSWORD_AUTH\",\n\t\"ClientId\": \"{{ _.clientID }}\"\n}"
         },
         "parameters":[
            
         ],
         "headers":[
            {
               "name":"Content-Type",
               "value":"application/x-amz-json-1.1",
               "id":"pair_72dd00b9aecc449191aa3ef0b9b76c02"
            },
            {
               "id":"pair_9e81734bb39f4a94aa142012bbc2c15a",
               "name":"X-Amz-Target",
               "value":"AWSCognitoIdentityProviderService.InitiateAuth",
               "description":""
            }
         ],
         "authentication":{
            
         },
         "metaSortKey":-1643632790143.75,
         "isPrivate":false,
         "settingStoreCookies":true,
         "settingSendCookies":true,
         "settingDisableRenderRequestBody":false,
         "settingEncodeUrl":true,
         "settingRebuildPath":true,
         "settingFollowRedirects":"global",
         "_type":"request"
      },
      {
         "_id":"req_840de14d46da4b119a0e5c0ff8c00155",
         "parentId":"wrk_4a5a7b0f3f1d40898c0652e42004d10c",
         "modified":1657573748749,
         "created":1651066904069,
         "url":"{{ _.cognito }}",
         "name":"Authenticate tenant",
         "description":"",
         "method":"POST",
         "body":{
            "mimeType":"application/json",
            "text":"{\n\t\"AuthParameters\": {\n\t\t\"USERNAME\": \"{{ _.tenant_user_name }}\",\n\t\t\"PASSWORD\": \"{{ _.tenant_password }}\"\n\t},\n\t\"AuthFlow\": \"USER_PASSWORD_AUTH\",\n\t\"ClientId\": \"{{ _.clientID }}\"\n}"
         },
         "parameters":[
            
         ],
         "headers":[
            {
               "name":"Content-Type",
               "value":"application/x-amz-json-1.1",
               "id":"pair_72dd00b9aecc449191aa3ef0b9b76c02"
            },
            {
               "id":"pair_9e81734bb39f4a94aa142012bbc2c15a",
               "name":"X-Amz-Target",
               "value":"AWSCognitoIdentityProviderService.InitiateAuth",
               "description":""
            }
         ],
         "authentication":{
            
         },
         "metaSortKey":-1643632790139.0625,
         "isPrivate":false,
         "settingStoreCookies":true,
         "settingSendCookies":true,
         "settingDisableRenderRequestBody":false,
         "settingEncodeUrl":true,
         "settingRebuildPath":true,
         "settingFollowRedirects":"global",
         "_type":"request"
      },
      {
         "_id":"req_f475cc1148354e2c9b4eaec37f479dac",
         "parentId":"wrk_4a5a7b0f3f1d40898c0652e42004d10c",
         "modified":1657573746829,
         "created":1652103507556,
         "url":"{{ _.graphql }}",
         "name":"Credit Account",
         "description":"",
         "method":"POST",
         "body":{
            "mimeType":"application/graphql",
            "text":"{\"query\":\"mutation CreditAccount {\\n\\tcreditAccount(\\n\\t\\tinput: {\\n\\t\\t\\tproviderId: \\\"{{ _.providerId }}\\\"\\n\\t\\t\\taccountId: \\\"{{ _.accountId }}\\\"\\n\\t\\t\\tamount: 1000\\n\\t\\t}\\n\\t) {\\n\\t\\t... on CreditAccountPayload {\\n\\t\\t\\t__typename\\n\\t\\t\\taccount {\\n\\t\\t\\t\\tbalance {\\n\\t\\t\\t\\t\\tcustomData\\n\\t\\t\\t\\t\\tvalue\\n\\t\\t\\t\\t\\tversion\\n\\t\\t\\t\\t}\\n\\t\\t\\t\\tcustomData\\n\\t\\t\\t\\tid\\n\\t\\t\\t}\\n\\t\\t}\\n\\t\\t... on AccountNotFound {\\n\\t\\t\\terrorMessage\\n\\t\\t\\taccountId\\n\\t\\t\\terrorCode\\n\\t\\t\\tproviderId\\n\\t\\t}\\n\\t\\t... on InvalidField {\\n\\t\\t\\terrorMessage\\n\\t\\t\\terrorCode\\n\\t\\t\\tfieldName\\n\\t\\t}\\n\\t}\\n}\\n\",\"operationName\":\"CreditAccount\"}"
         },
         "parameters":[
            {
               "id":"pair_bf2536dcb0da422c89fee6902d42989d",
               "name":"",
               "value":"",
               "description":""
            }
         ],
         "headers":[
            {
               "name":"Content-Type",
               "value":"application/json",
               "id":"pair_fb6a84bf29ab4f4aac06f321b86cab55"
            },
            {
               "id":"pair_5941090f2b424f96bec5d96be195da01",
               "name":"Authorization",
               "value":"{% response 'body', 'req_76f28bad434041c78a1d8e79c9fc80a8', 'b64::JC5BdXRoZW50aWNhdGlvblJlc3VsdC5JZFRva2Vu::46b', 'when-expired', 3000 %}",
               "description":""
            }
         ],
         "authentication":{
            
         },
         "metaSortKey":-1643632790136.7188,
         "isPrivate":false,
         "settingStoreCookies":true,
         "settingSendCookies":true,
         "settingDisableRenderRequestBody":false,
         "settingEncodeUrl":true,
         "settingRebuildPath":true,
         "settingFollowRedirects":"global",
         "_type":"request"
      },
      {
         "_id":"req_8e148f3465144c09ac35a07536f1b722",
         "parentId":"wrk_4a5a7b0f3f1d40898c0652e42004d10c",
         "modified":1657573746206,
         "created":1643632777100,
         "url":"{{ _.graphql }}",
         "name":"Create Account",
         "description":"",
         "method":"POST",
         "body":{
            "mimeType":"application/graphql",
            "text":"{\"query\":\"mutation CreateAccount {\\n\\tcreateAccount(\\n\\t\\tinput: { accountId: \\\"{{ _.accountId }}\\\", providerId: \\\"{{ _.providerId }}\\\" }\\n\\t) {\\n\\t\\t... on InvalidField {\\n\\t\\t\\terrorMessage\\n\\t\\t\\tfieldName\\n\\t\\t\\terrorCode\\n\\t\\t}\\n\\t\\t... on AccountAlreadyExists {\\n\\t\\t\\terrorMessage\\n\\t\\t\\terrorCode\\n\\t\\t\\taccountId\\n\\t\\t}\\n\\t\\t... on AccountNotFound {\\n\\t\\t\\terrorMessage\\n\\t\\t\\taccountId\\n\\t\\t\\terrorCode\\n\\t\\t\\tproviderId\\n\\t\\t}\\n\\t\\t... on CreateAccountPayload {\\n\\t\\t\\t__typename\\n\\t\\t\\taccount {\\n\\t\\t\\t\\tid\\n\\t\\t\\t\\tproviderId\\n\\t\\t\\t}\\n\\t\\t}\\n\\t}\\n}\\n\",\"operationName\":\"CreateAccount\"}"
         },
         "parameters":[
            
         ],
         "headers":[
            {
               "name":"Content-Type",
               "value":"application/json",
               "id":"pair_fb6a84bf29ab4f4aac06f321b86cab55"
            },
            {
               "id":"pair_5941090f2b424f96bec5d96be195da01",
               "name":"Authorization",
               "value":"{% response 'body', 'req_76f28bad434041c78a1d8e79c9fc80a8', 'b64::JC5BdXRoZW50aWNhdGlvblJlc3VsdC5JZFRva2Vu::46b', 'when-expired', 3000 %}",
               "description":""
            }
         ],
         "authentication":{
            
         },
         "metaSortKey":-1643632790134.375,
         "isPrivate":false,
         "settingStoreCookies":true,
         "settingSendCookies":true,
         "settingDisableRenderRequestBody":false,
         "settingEncodeUrl":true,
         "settingRebuildPath":true,
         "settingFollowRedirects":"global",
         "_type":"request"
      },
      {
         "_id":"req_a686c3732c524d03915e140547ecaf09",
         "parentId":"wrk_4a5a7b0f3f1d40898c0652e42004d10c",
         "modified":1657573744846,
         "created":1643632784347,
         "url":"{{ _.graphql }}",
         "name":"Get Account",
         "description":"",
         "method":"POST",
         "body":{
            "mimeType":"application/graphql",
            "text":"{\"query\":\"query GetAccount {\\n\\tgetAccount(accountId: \\\"{{ _.accountId }}\\\", providerId: \\\"{{ _.providerId }}\\\") {\\n    ... on AccountNotFound {\\n      errorMessage\\n      providerId\\n      errorCode\\n      accountId\\n    }\\n    ... on Account {\\n      id\\n      customData\\n      providerId\\n      balance {\\n        customData\\n        value\\n        version\\n      }\\n\\t\\t\\tactivePlanVersions{\\n\\t\\t\\t\\tfrom\\n\\t\\t\\t\\tto\\n\\t\\t\\t\\tplanVersion{\\n\\t\\t\\t\\t\\tid\\n\\t\\t\\t\\t\\tversion\\n          planServices{\\n\\t\\t\\t\\t\\t\\tbalanceName\\n\\t\\t\\t\\t\\t}\\n\\t\\t\\t\\t}\\n\\t\\t\\t}\\n\\t\\t\\tarchivedPlanVersions{\\n\\t\\t\\t\\tfrom\\n\\t\\t\\t\\tto\\n\\t\\t\\t\\tplanVersion{\\n\\t\\t\\t\\t\\tid\\n\\t\\t\\t\\t\\tversion\\n          planServices{\\n\\t\\t\\t\\t\\t\\tbalanceName\\n\\t\\t\\t\\t\\t}\\n\\t\\t\\t\\t}\\n\\t\\t\\t}\\n\\t\\t}\\n\\t}\\n}\",\"operationName\":\"GetAccount\"}"
         },
         "parameters":[
            
         ],
         "headers":[
            {
               "name":"Content-Type",
               "value":"application/json",
               "id":"pair_308ee14452f6472e8a2c5f71e3a032a2"
            },
            {
               "id":"pair_c108ba0bc84e48f7bf5f812958b3a7df",
               "name":"Authorization",
               "value":"{% response 'body', 'req_76f28bad434041c78a1d8e79c9fc80a8', 'b64::JC5BdXRoZW50aWNhdGlvblJlc3VsdC5JZFRva2Vu::46b', 'when-expired', 3000 %}",
               "description":""
            }
         ],
         "authentication":{
            
         },
         "metaSortKey":-1643632790131.25,
         "isPrivate":false,
         "settingStoreCookies":true,
         "settingSendCookies":true,
         "settingDisableRenderRequestBody":false,
         "settingEncodeUrl":true,
         "settingRebuildPath":true,
         "settingFollowRedirects":"global",
         "_type":"request"
      },
      {
         "_id":"req_87cffc14f82948e9b9860e72e6fe298f",
         "parentId":"wrk_4a5a7b0f3f1d40898c0652e42004d10c",
         "modified":1657573743697,
         "created":1654729723655,
         "url":"{{ _.graphql }}",
         "name":"getEventDataRecordsByDevice",
         "description":"",
         "method":"POST",
         "body":{
            "mimeType":"application/graphql",
            "text":"{\"query\":\"query getEventDataRecordsByDevice {\\n\\tgetEventDataRecordsByDevice(\\n\\t\\tproviderId: \\\"{{ _.providerId }}\\\",\\n\\t\\tdeviceId: \\\"{{ _.deviceId }}\\\",\\n\\t\\tfirst: 100,\\n\\t\\tfilterBy: {\\n\\t\\t\\ttypes: [CHARGING, BILLING],\\n\\t\\t\\tfrom: \\\"2022-06-29T17:28:00.000Z\\\",\\n\\t\\t\\tto: \\\"2022-08-01T00:00:00.000Z\\\"\\n\\t})\\n{\\n\\t\\t\\t... on EventDataRecordDeviceConnection{\\n            edges{\\n                node{\\n                    customData\\n                    id\\n                }\\n                cursor\\n            }\\n            pageInfo{\\n            hasPreviousPage\\n            hasNextPage\\n            startCursor\\n            endCursor\\n            }\\n        }\\n        ... on DeviceNotFound{\\n            providerId\\n            deviceId\\n            errorCode\\n            errorMessage\\n        }\\n    }\\n}\",\"operationName\":\"getEventDataRecordsByDevice\"}"
         },
         "parameters":[
            
         ],
         "headers":[
            {
               "name":"Content-Type",
               "value":"application/json",
               "id":"pair_308ee14452f6472e8a2c5f71e3a032a2"
            },
            {
               "id":"pair_c108ba0bc84e48f7bf5f812958b3a7df",
               "name":"Authorization",
               "value":"{% response 'body', 'req_76f28bad434041c78a1d8e79c9fc80a8', 'b64::JC5BdXRoZW50aWNhdGlvblJlc3VsdC5JZFRva2Vu::46b', 'when-expired', 3000 %}",
               "description":""
            }
         ],
         "authentication":{
            
         },
         "metaSortKey":-1643632790128.125,
         "isPrivate":false,
         "settingStoreCookies":true,
         "settingSendCookies":true,
         "settingDisableRenderRequestBody":false,
         "settingEncodeUrl":true,
         "settingRebuildPath":true,
         "settingFollowRedirects":"global",
         "_type":"request"
      },
      {
         "_id":"req_04c63e8691a54ff19f7480f8b0c78ece",
         "parentId":"wrk_4a5a7b0f3f1d40898c0652e42004d10c",
         "modified":1657573737380,
         "created":1654733202811,
         "url":"{{ _.graphql }}",
         "name":"getEventDataRecordsByAccount",
         "description":"",
         "method":"POST",
         "body":{
            "mimeType":"application/graphql",
            "text":"{\"query\":\"query getEventDataRecordsByAccount {\\n\\tgetEventDataRecordsByAccount(providerId: \\\"{{ _.providerId }}\\\", accountId: \\\"{{ _.deviceId }}\\\", first: 100, filterBy: {\\n\\t\\ttypes: [CHARGING, BILLING],\\n\\t\\tfrom: \\\"2022-06-29T17:28:00.000Z\\\",\\n\\t\\tto: \\\"2022-08-01T00:00:00.000Z\\\"\\n\\t})\\n{\\n\\t\\t\\t... on EventDataRecordAccountConnection{\\n            account{\\n                providerId\\n                customData\\n                balance{\\n                    version\\n                    value\\n                    customData\\n                }\\n            }\\n            edges{\\n                node{\\n                    createdAt\\n                    customData\\n                    id\\n                }\\n                cursor\\n            }\\n            pageInfo{\\n            hasPreviousPage\\n            hasNextPage\\n            startCursor\\n            endCursor\\n            }\\n        }\\n        ... on AccountNotFound {\\n            providerId\\n            accountId\\n            errorCode\\n            errorMessage\\n        }\\n    }\\n}\",\"operationName\":\"getEventDataRecordsByAccount\"}"
         },
         "parameters":[
            
         ],
         "headers":[
            {
               "name":"Content-Type",
               "value":"application/json",
               "id":"pair_308ee14452f6472e8a2c5f71e3a032a2"
            },
            {
               "id":"pair_c108ba0bc84e48f7bf5f812958b3a7df",
               "name":"Authorization",
               "value":"{% response 'body', 'req_76f28bad434041c78a1d8e79c9fc80a8', 'b64::JC5BdXRoZW50aWNhdGlvblJlc3VsdC5JZFRva2Vu::46b', 'when-expired', 3000 %}",
               "description":""
            }
         ],
         "authentication":{
            
         },
         "metaSortKey":-1643632790126.5625,
         "isPrivate":false,
         "settingStoreCookies":true,
         "settingSendCookies":true,
         "settingDisableRenderRequestBody":false,
         "settingEncodeUrl":true,
         "settingRebuildPath":true,
         "settingFollowRedirects":"global",
         "_type":"request"
      },
      {
         "_id":"req_7f18a27191b54238a4530f9905c425b3",
         "parentId":"wrk_4a5a7b0f3f1d40898c0652e42004d10c",
         "modified":1657573727151,
         "created":1643632790125,
         "url":"{{ _.graphql }}",
         "name":"Delete Account",
         "description":"",
         "method":"POST",
         "body":{
            "mimeType":"application/graphql",
            "text":"{\"query\":\"mutation DeleteAccount {\\n\\tdeleteAccount(\\n\\t\\tinput: { accountId: \\\"{{ _.accountId }}\\\", providerId: \\\"{{ _.providerId }}\\\" }\\n\\t) {\\n\\t\\t... on AccountHasReferences {\\n\\t\\t\\terrorMessage\\n\\t\\t\\tproviderId\\n\\t\\t\\terrorCode\\n\\t\\t\\taccountId\\n\\t\\t}\\n\\t\\t... on AccountNotFound {\\n\\t\\t\\terrorMessage\\n\\t\\t\\tproviderId\\n\\t\\t\\taccountId\\n\\t\\t\\terrorCode\\n\\t\\t}\\n\\t\\t... on DeleteAccountPayload {\\n\\t\\t\\t__typename\\n\\t\\t\\tdeletedAccountId\\n\\t\\t\\tparentAccount {\\n        providerId\\n        id\\n        friendsAndFamily\\n        customData\\n      }\\n\\t\\t}\\n\\t}\\n}\\n\",\"operationName\":\"DeleteAccount\"}"
         },
         "parameters":[
            
         ],
         "headers":[
            {
               "name":"Content-Type",
               "value":"application/json",
               "id":"pair_0fdc8d25f00946edb280b049ee9a3adb"
            },
            {
               "id":"pair_9640fedbed0a469ebfa88b80a6669506",
               "name":"Authorization",
               "value":"{% response 'body', 'req_76f28bad434041c78a1d8e79c9fc80a8', 'b64::JC5BdXRoZW50aWNhdGlvblJlc3VsdC5JZFRva2Vu::46b', 'when-expired', 3000 %}",
               "description":""
            }
         ],
         "authentication":{
            
         },
         "metaSortKey":-1643632790125,
         "isPrivate":false,
         "settingStoreCookies":true,
         "settingSendCookies":true,
         "settingDisableRenderRequestBody":false,
         "settingEncodeUrl":true,
         "settingRebuildPath":true,
         "settingFollowRedirects":"global",
         "_type":"request"
      },
      {
         "_id":"req_e6bfe0229d5547278a42f32f28212a35",
         "parentId":"wrk_4a5a7b0f3f1d40898c0652e42004d10c",
         "modified":1657573726567,
         "created":1643633574991,
         "url":"{{ _.graphql }}",
         "name":"Create Device",
         "description":"",
         "method":"POST",
         "body":{
            "mimeType":"application/graphql",
            "text":"{\"query\":\"mutation CreateDevice {\\n\\tcreateDevice(\\n\\t\\tinput: {\\n\\t\\t\\taccountId: \\\"{{ _.accountId }}\\\"\\n\\t\\t\\tproviderId: \\\"{{ _.providerId }}\\\"\\n\\t\\t\\tdeviceId: \\\"{{ _.deviceId }}\\\"\\n\\t\\t}\\n\\t) {\\n    ... on CreateDevicePayload {\\n      __typename\\n      device {\\n        providerId\\n        id\\n        customData\\n        account {\\n          id\\n          providerId\\n        }\\n      }\\n    }\\n    ... on DeviceAlreadyExists {\\n      errorMessage\\n      errorCode\\n      deviceId\\n    }\\n    ... on AccountNotFound {\\n      errorMessage\\n      providerId\\n      errorCode\\n      accountId\\n    }\\n    ... on InvalidField {\\n      errorMessage\\n      fieldName\\n      errorCode\\n    }\\n  }\\n}\\n\",\"operationName\":\"CreateDevice\"}"
         },
         "parameters":[
            
         ],
         "headers":[
            {
               "name":"Content-Type",
               "value":"application/json",
               "id":"pair_f780cb6b5aa54669ad37f44371033c9b"
            },
            {
               "id":"pair_30ad19199adf453d8a73338add56a9cf",
               "name":"Authorization",
               "value":"{% response 'body', 'req_76f28bad434041c78a1d8e79c9fc80a8', 'b64::JC5BdXRoZW50aWNhdGlvblJlc3VsdC5JZFRva2Vu::46b', 'when-expired', 3000 %}",
               "description":""
            }
         ],
         "authentication":{
            
         },
         "metaSortKey":-1643630378289.25,
         "isPrivate":false,
         "settingStoreCookies":true,
         "settingSendCookies":true,
         "settingDisableRenderRequestBody":false,
         "settingEncodeUrl":true,
         "settingRebuildPath":true,
         "settingFollowRedirects":"global",
         "_type":"request"
      },
      {
         "_id":"req_de45211a8ea34022af1a08ce4f508df9",
         "parentId":"wrk_4a5a7b0f3f1d40898c0652e42004d10c",
         "modified":1657573725635,
         "created":1643633778091,
         "url":"{{ _.graphql }}",
         "name":"Get Device",
         "description":"",
         "method":"POST",
         "body":{
            "mimeType":"application/graphql",
            "text":"{\"query\":\"query GetDevice {\\n\\tgetDevice(providerId: \\\"{{ _.providerId }}\\\", deviceId: \\\"{{ _.deviceId }}\\\") {\\n\\t\\t... on DeviceNotFound {\\n\\t\\t\\terrorMessage\\n\\t\\t\\tproviderId\\n\\t\\t\\terrorCode\\n\\t\\t\\tdeviceId\\n\\t\\t}\\n\\t\\t... on Device {\\n\\t\\t\\tid\\n\\t\\t\\tproviderId\\n      customData\\n\\t\\t\\taccount {\\n\\t\\t\\t\\tid\\n\\t\\t\\t\\tproviderId\\n\\t\\t\\t}\\n\\t\\t}\\n\\t}\\n}\\n\",\"operationName\":\"GetDevice\"}"
         },
         "parameters":[
            
         ],
         "headers":[
            {
               "name":"Content-Type",
               "value":"application/json",
               "id":"pair_f3e619215be94b1493f5d42c8dbd559f"
            },
            {
               "id":"pair_b59d1f567542453e856e0f293b3653f6",
               "name":"Authorization",
               "value":"{% response 'body', 'req_76f28bad434041c78a1d8e79c9fc80a8', 'b64::JC5BdXRoZW50aWNhdGlvblJlc3VsdC5JZFRva2Vu::46b', 'when-expired', 3000 %}",
               "description":""
            }
         ],
         "authentication":{
            
         },
         "metaSortKey":-1643629172371.375,
         "isPrivate":false,
         "settingStoreCookies":true,
         "settingSendCookies":true,
         "settingDisableRenderRequestBody":false,
         "settingEncodeUrl":true,
         "settingRebuildPath":true,
         "settingFollowRedirects":"global",
         "_type":"request"
      },
      {
         "_id":"req_0960b625c3b040af8c9a801eab76acee",
         "parentId":"wrk_4a5a7b0f3f1d40898c0652e42004d10c",
         "modified":1657573724886,
         "created":1643633782058,
         "url":"{{ _.graphql }}",
         "name":"Delete Device",
         "description":"",
         "method":"POST",
         "body":{
            "mimeType":"application/graphql",
            "text":"{\"query\":\"mutation DeleteDevice {\\n\\tdeleteDevice(\\n\\t\\tinput: {\\n\\t\\t\\taccountId: \\\"{{ _.accountId }}\\\"\\n\\t\\t\\tproviderId: \\\"{{ _.providerId }}\\\"\\n\\t\\t\\tdeviceId: \\\"{{ _.deviceId }}\\\"\\n\\t\\t}\\n\\t) {\\n\\t\\t... on DeviceNotFound {\\n\\t\\t\\terrorMessage\\n\\t\\t\\tproviderId\\n\\t\\t\\terrorCode\\n\\t\\t\\tdeviceId\\n\\t\\t}\\n\\t\\t... on DeleteDevicePayload {\\n\\t\\t\\t__typename\\n\\t\\t\\tdeletedDeviceId\\n\\t\\t\\taccount {\\n\\t\\t\\t\\tproviderId\\n\\t\\t\\t\\tid\\n\\t\\t\\t}\\n\\t\\t}\\n\\t}\\n}\\n\",\"operationName\":\"DeleteDevice\"}"
         },
         "parameters":[
            
         ],
         "headers":[
            {
               "name":"Content-Type",
               "value":"application/json",
               "id":"pair_8df40533a031404f89627fc4aea28dd7"
            },
            {
               "id":"pair_3fb323536908408fac212eda4623c62e",
               "name":"Authorization",
               "value":"{% response 'body', 'req_76f28bad434041c78a1d8e79c9fc80a8', 'b64::JC5BdXRoZW50aWNhdGlvblJlc3VsdC5JZFRva2Vu::46b', 'when-expired', 3000 %}",
               "description":""
            }
         ],
         "authentication":{
            
         },
         "metaSortKey":-1643628569412.4375,
         "isPrivate":false,
         "settingStoreCookies":true,
         "settingSendCookies":true,
         "settingDisableRenderRequestBody":false,
         "settingEncodeUrl":true,
         "settingRebuildPath":true,
         "settingFollowRedirects":"global",
         "_type":"request"
      },
      {
         "_id":"req_e94f8fcd1e3c481480916f8100fa8ae5",
         "parentId":"wrk_4a5a7b0f3f1d40898c0652e42004d10c",
         "modified":1657573719166,
         "created":1643299884748,
         "url":"{{ _.graphql }}",
         "name":"Get plan",
         "description":"",
         "method":"POST",
         "body":{
            "mimeType":"application/graphql",
            "text":"{\"query\":\"query GetPlan {\\n\\tgetPlan(\\n\\t\\tplanId: \\\"{{ _.planId }}\\\"\\n\\t\\tproviderId: \\\"{{ _.providerId }}\\\"\\n\\t) {\\n\\t\\t... on PlanNotFound {\\n\\t\\t\\terrorMessage\\n\\t\\t\\terrorCode\\n\\t\\t\\tplanId\\n\\t\\t\\tproviderId\\n\\t\\t}\\n\\t\\t... on Plan {\\n\\t\\t\\tid\\n\\t\\t\\tname\\n\\t\\t\\tproviderId\\n\\t\\t\\tversions(first: 10) {\\n\\t\\t\\t\\tpageInfo {\\n\\t\\t\\t\\t\\tstartCursor\\n\\t\\t\\t\\t\\tendCursor\\n\\t\\t\\t\\t}\\n\\t\\t\\t\\tedges {\\n\\t\\t\\t\\t\\tnode {\\n\\t\\t\\t\\t\\t\\tcreatedAt\\n\\t\\t\\t\\t\\t\\tcreatedBy\\n\\t\\t\\t\\t\\t\\tdeployedAt\\n\\t\\t\\t\\t\\t\\tdeployedBy\\n\\t\\t\\t\\t\\t\\tid\\n\\t\\t\\t\\t\\t\\tmodifiedAt\\n\\t\\t\\t\\t\\t\\tmodifiedBy\\n\\t\\t\\t\\t\\t\\tpriority\\n\\t\\t\\t\\t\\t\\trefCount\\n\\t\\t\\t\\t\\t\\tstate\\n\\t\\t\\t\\t\\t\\tversion\\n\\t\\t\\t\\t\\t\\tplanServices {\\n\\t\\t\\t\\t\\t\\t\\tbalanceName\\n\\t\\t\\t\\t\\t\\t\\tid\\n\\t\\t\\t\\t\\t\\t\\tname\\n\\t\\t\\t\\t\\t\\t\\tratingGroupId\\n\\t\\t\\t\\t\\t\\t\\tprovidedFields {\\n\\t\\t\\t\\t\\t\\t\\t\\tcustomData\\n\\t\\t\\t\\t\\t\\t\\t\\tdataType\\n\\t\\t\\t\\t\\t\\t\\t\\tname\\n\\t\\t\\t\\t\\t\\t\\t}\\n\\t\\t\\t\\t\\t\\t\\truleSets {\\n\\t\\t\\t\\t\\t\\t\\t\\tcharging {\\n\\t\\t\\t\\t\\t\\t\\t\\t\\tid\\n\\t\\t\\t\\t\\t\\t\\t\\t\\tname\\n\\t\\t\\t\\t\\t\\t\\t\\t\\tpluginId\\n\\t\\t\\t\\t\\t\\t\\t\\t}\\n\\t\\t\\t\\t\\t\\t\\t\\tcrediting {\\n\\t\\t\\t\\t\\t\\t\\t\\t\\tid\\n\\t\\t\\t\\t\\t\\t\\t\\t\\tname\\n\\t\\t\\t\\t\\t\\t\\t\\t\\tpluginId\\n\\t\\t\\t\\t\\t\\t\\t\\t}\\n\\t\\t\\t\\t\\t\\t\\t\\trecurring {\\n\\t\\t\\t\\t\\t\\t\\t\\t\\tid\\n\\t\\t\\t\\t\\t\\t\\t\\t\\tname\\n\\t\\t\\t\\t\\t\\t\\t\\t\\tpluginId\\n\\t\\t\\t\\t\\t\\t\\t\\t}\\n\\t\\t\\t\\t\\t\\t\\t}\\n\\t\\t\\t\\t\\t\\t}\\n\\t\\t\\t\\t\\t\\tcounters {\\n\\t\\t\\t\\t\\t\\t\\tincrement\\n\\t\\t\\t\\t\\t\\t\\tname\\n\\t\\t\\t\\t\\t\\t\\tnotificationFields\\n\\t\\t\\t\\t\\t\\t\\tpersistent\\n\\t\\t\\t\\t\\t\\t\\tselector\\n\\t\\t\\t\\t\\t\\t\\tperiod {\\n\\t\\t\\t\\t\\t\\t\\t\\tdata\\n\\t\\t\\t\\t\\t\\t\\t\\ttype\\n\\t\\t\\t\\t\\t\\t\\t}\\n\\t\\t\\t\\t\\t\\t\\tstates {\\n\\t\\t\\t\\t\\t\\t\\t\\tname\\n\\t\\t\\t\\t\\t\\t\\t\\tthreshold\\n\\t\\t\\t\\t\\t\\t\\t}\\n\\t\\t\\t\\t\\t\\t}\\n\\t\\t\\t\\t\\t}\\n\\t\\t\\t\\t}\\n\\t\\t\\t}\\n\\t\\t}\\n\\t}\\n}\\n\",\"operationName\":\"GetPlan\"}"
         },
         "parameters":[
            
         ],
         "headers":[
            {
               "name":"Content-Type",
               "value":"application/json",
               "id":"pair_ec1ee84bba3a4d44b149a88c7268a3c5"
            },
            {
               "id":"pair_fc828fed3cc140e486f9399700b70b74",
               "name":"Authorization",
               "value":"{% response 'body', 'req_108b6d87926b4a1da95a1393d138ce93', 'b64::JC5BdXRoZW50aWNhdGlvblJlc3VsdC5JZFRva2Vu::46b', 'when-expired', 3000 %}",
               "description":""
            }
         ],
         "authentication":{
            
         },
         "metaSortKey":-1643627966453.5,
         "isPrivate":false,
         "settingStoreCookies":true,
         "settingSendCookies":true,
         "settingDisableRenderRequestBody":false,
         "settingEncodeUrl":true,
         "settingRebuildPath":true,
         "settingFollowRedirects":"global",
         "_type":"request"
      },
      {
         "_id":"req_642ee09ab881402bb8df43d46553fa03",
         "parentId":"wrk_4a5a7b0f3f1d40898c0652e42004d10c",
         "modified":1657573718526,
         "created":1643648509983,
         "url":"{{ _.graphql }}",
         "name":"Get plan version",
         "description":"",
         "method":"POST",
         "body":{
            "mimeType":"application/graphql",
            "text":"{\"query\":\"query GetPlanVersion {\\n\\tgetPlanVersion(\\n\\t\\tplanVersionId: \\\"{{ _.versionId }}\\\"\\n\\t\\tproviderId: \\\"{{ _.providerId }}\\\"\\n\\t) {\\n\\t\\t... on PlanVersionNotFound {\\n\\t\\t\\terrorMessage\\n\\t\\t\\terrorCode\\n\\t\\t\\tplanVersionId\\n\\t\\t\\tproviderId\\n\\t\\t}\\n\\t\\t... on PlanVersion {\\n\\t\\t\\tid\\n\\t\\t\\tversion\\n\\t\\t\\tcreatedAt\\n\\t\\t\\tcreatedBy\\n\\t\\t\\tdeployedAt\\n\\t\\t\\tdeployedBy\\n\\t\\t\\tmodifiedAt\\n\\t\\t\\tmodifiedBy\\n\\t\\t\\tplanServices {\\n\\t\\t\\t\\tid\\n\\t\\t\\t\\tname\\n\\t\\t\\t\\tbalanceName\\n\\t\\t\\t\\tratingGroupId\\n\\t\\t\\t\\tprovidedFields {\\n\\t\\t\\t\\t\\tname\\n\\t\\t\\t\\t\\tcustomData\\n\\t\\t\\t\\t\\tdataType\\n\\t\\t\\t\\t}\\n\\t\\t\\t\\truleSets {\\n\\t\\t\\t\\t\\trecurring {\\n\\t\\t\\t\\t\\t\\tpluginId\\n\\t\\t\\t\\t\\t\\tname\\n\\t\\t\\t\\t\\t\\tid\\n\\t\\t\\t\\t\\t}\\n\\t\\t\\t\\t\\tcrediting {\\n\\t\\t\\t\\t\\t\\tid\\n\\t\\t\\t\\t\\t\\tname\\n\\t\\t\\t\\t\\t\\tpluginId\\n\\t\\t\\t\\t\\t}\\n\\t\\t\\t\\t\\tcharging {\\n\\t\\t\\t\\t\\t\\tpluginId\\n\\t\\t\\t\\t\\t\\tname\\n\\t\\t\\t\\t\\t\\tid\\n\\t\\t\\t\\t\\t}\\n\\t\\t\\t\\t}\\n\\t\\t\\t}\\n\\t\\t\\tplan {\\n\\t\\t\\t\\tid\\n\\t\\t\\t\\tname\\n\\t\\t\\t}\\n\\t\\t\\tcounters {\\n\\t\\t\\t\\tincrement\\n\\t\\t\\t\\tname\\n\\t\\t\\t\\tnotificationFields\\n\\t\\t\\t\\tpersistent\\n\\t\\t\\t\\tselector\\n\\t\\t\\t\\tperiod {\\n\\t\\t\\t\\t\\tdata\\n\\t\\t\\t\\t\\ttype\\n\\t\\t\\t\\t}\\n\\t\\t\\t\\tstates {\\n\\t\\t\\t\\t\\tname\\n\\t\\t\\t\\t\\tthreshold\\n\\t\\t\\t\\t}\\n\\t\\t\\t}\\n\\t\\t}\\n\\t}\\n}\\n\",\"operationName\":\"GetPlanVersion\"}"
         },
         "parameters":[
            
         ],
         "headers":[
            {
               "name":"Content-Type",
               "value":"application/json",
               "id":"pair_ec1ee84bba3a4d44b149a88c7268a3c5"
            },
            {
               "id":"pair_fc828fed3cc140e486f9399700b70b74",
               "name":"Authorization",
               "value":"{% response 'body', 'req_108b6d87926b4a1da95a1393d138ce93', 'b64::JC5BdXRoZW50aWNhdGlvblJlc3VsdC5JZFRva2Vu::46b', 'when-expired', 3000 %}",
               "description":""
            }
         ],
         "authentication":{
            
         },
         "metaSortKey":-1643627363494.5625,
         "isPrivate":false,
         "settingStoreCookies":true,
         "settingSendCookies":true,
         "settingDisableRenderRequestBody":false,
         "settingEncodeUrl":true,
         "settingRebuildPath":true,
         "settingFollowRedirects":"global",
         "_type":"request"
      },
      {
         "_id":"req_2f8a64e2997647118908bdbb68eadf2b",
         "parentId":"wrk_4a5a7b0f3f1d40898c0652e42004d10c",
         "modified":1657573713369,
         "created":1643637916751,
         "url":"{{ _.graphql }}",
         "name":"Get Plans",
         "description":"",
         "method":"POST",
         "body":{
            "mimeType":"application/graphql",
            "text":"{\"query\":\"query GetPlans {\\n\\tgetPlans(first: 2, after: \\\"1\\\", providerId: \\\"{{_.providerId}}\\\") {\\n    edges {\\n      node {\\n        id\\n        name\\n        versions(first: 500) {\\n          edges {\\n            node {\\n              version\\n              state\\n              id\\n            }\\n          }\\n        }\\n      }\\n    }\\n\\t\\tpageInfo {\\n\\t\\t\\thasPreviousPage\\n\\t\\t\\thasNextPage\\n\\t\\t\\tstartCursor\\n\\t\\t\\tendCursor\\n\\t\\t}\\n  }\\n}\\n\",\"operationName\":\"GetPlans\"}"
         },
         "parameters":[
            
         ],
         "headers":[
            {
               "name":"Content-Type",
               "value":"application/json",
               "id":"pair_de193f73e7b5491bb7428f278e428233"
            },
            {
               "id":"pair_de56734f3b8a429eb9076ef58af34fee",
               "name":"Authorization",
               "value":"{% response 'body', 'req_108b6d87926b4a1da95a1393d138ce93', 'b64::JC5BdXRoZW50aWNhdGlvblJlc3VsdC5JZFRva2Vu::46b', 'when-expired', 3000 %}",
               "description":""
            }
         ],
         "authentication":{
            
         },
         "metaSortKey":-1643626760535.625,
         "isPrivate":false,
         "settingStoreCookies":true,
         "settingSendCookies":true,
         "settingDisableRenderRequestBody":false,
         "settingEncodeUrl":true,
         "settingRebuildPath":true,
         "settingFollowRedirects":"global",
         "_type":"request"
      },
      {
         "_id":"req_68a0451dda494bc487741a420768d322",
         "parentId":"wrk_4a5a7b0f3f1d40898c0652e42004d10c",
         "modified":1657573698847,
         "created":1643710089643,
         "url":"{{ _.graphql }}",
         "name":"Delete Plan Version",
         "description":"",
         "method":"POST",
         "body":{
            "mimeType":"application/graphql",
            "text":"{\"query\":\"mutation DeletePlanVersion {\\n\\tdeletePlanVersion(\\n\\t\\tinput: {\\n\\t\\t\\tproviderId: \\\"{{ _.providerId }}\\\"\\n\\t\\t\\tplanVersionId: \\\"{{ _.versionId }}\\\"\\n\\t\\t}\\n\\t) {\\n\\t\\t... on PlanVersionHasReferences {\\n\\t\\t\\terrorMessage\\n\\t\\t\\terrorCode\\n\\t\\t\\tplanVersion {\\n\\t\\t\\t\\tid\\n\\t\\t\\t\\tversion\\n\\t\\t\\t\\tstate\\n\\t\\t\\t}\\n\\t\\t}\\n\\t\\t... on PlanVersionNotFound {\\n\\t\\t\\terrorMessage\\n\\t\\t\\tproviderId\\n\\t\\t\\tplanVersionId\\n\\t\\t\\terrorCode\\n\\t\\t}\\n\\t\\t... on DeletePlanVersionPayload {\\n\\t\\t\\t__typename\\n\\t\\t\\tdeletedPlanVersionId\\n\\t\\t\\tplan {\\n\\t\\t\\t\\tproviderId\\n\\t\\t\\t\\tid\\n\\t\\t\\t\\tname\\n\\t\\t\\t\\tversions(first: 10) {\\n\\t\\t\\t\\t\\tedges {\\n\\t\\t\\t\\t\\t\\tnode {\\n\\t\\t\\t\\t\\t\\t\\tversion\\n\\t\\t\\t\\t\\t\\t\\tstate\\n\\t\\t\\t\\t\\t\\t\\tid\\n\\t\\t\\t\\t\\t\\t}\\n\\t\\t\\t\\t\\t}\\n\\t\\t\\t\\t}\\n\\t\\t\\t}\\n\\t\\t}\\n\\t}\\n}\\n\",\"operationName\":\"DeletePlanVersion\"}"
         },
         "parameters":[
            
         ],
         "headers":[
            {
               "name":"Content-Type",
               "value":"application/json",
               "id":"pair_b71d92dd37274f19844c0b5c5bc7ead7"
            },
            {
               "id":"pair_dd3a015f4b2143bc8ec7149cf9f31e36",
               "name":"Authorization",
               "value":"{% response 'body', 'req_108b6d87926b4a1da95a1393d138ce93', 'b64::JC5BdXRoZW50aWNhdGlvblJlc3VsdC5JZFRva2Vu::46b', 'when-expired', 3000 %}",
               "description":""
            }
         ],
         "authentication":{
            
         },
         "metaSortKey":-1643626157576.6875,
         "isPrivate":false,
         "settingStoreCookies":true,
         "settingSendCookies":true,
         "settingDisableRenderRequestBody":false,
         "settingEncodeUrl":true,
         "settingRebuildPath":true,
         "settingFollowRedirects":"global",
         "_type":"request"
      },
      {
         "_id":"req_43aa364b319a4132bc616d1ea3ff362f",
         "parentId":"wrk_4a5a7b0f3f1d40898c0652e42004d10c",
         "modified":1657573698225,
         "created":1643635705967,
         "url":"{{ _.graphql }}",
         "name":"Delete Plan",
         "description":"",
         "method":"POST",
         "body":{
            "mimeType":"application/graphql",
            "text":"{\"query\":\"mutation DeletePlan {\\n\\tdeletePlan(\\n\\t\\tinput: { planId: \\\"{{ _.planId }}\\\", providerId: \\\"{{ _.providerId }}\\\" }\\n\\t) {\\n\\t\\t... on PlanIsReadOnly {\\n\\t\\t\\terrorMessage\\n\\t\\t\\tproviderId\\n\\t\\t\\tplanId\\n\\t\\t\\terrorCode\\n\\t\\t}\\n\\t\\t... on PlanVersionHasReferences {\\n\\t\\t\\terrorMessage\\n\\t\\t\\terrorCode\\n\\t\\t\\tplanVersion {\\n\\t\\t\\t\\tid\\n\\t\\t\\t\\tversion\\n\\t\\t\\t\\tproviderId\\n\\t\\t\\t}\\n\\t\\t}\\n\\t\\t... on PlanNotFound {\\n\\t\\t\\terrorMessage\\n\\t\\t\\tproviderId\\n\\t\\t\\tplanId\\n\\t\\t\\terrorCode\\n\\t\\t}\\n\\t\\t... on DeletePlanPayload {\\n\\t\\t\\t__typename\\n\\t\\t\\tdeletedPlanServices\\n\\t\\t\\tdeletedPlanId\\n\\t\\t\\tdeletedPlanVersions\\n\\t\\t}\\n\\t}\\n}\\n\",\"operationName\":\"DeletePlan\"}"
         },
         "parameters":[
            
         ],
         "headers":[
            {
               "name":"Content-Type",
               "value":"application/json",
               "id":"pair_b71d92dd37274f19844c0b5c5bc7ead7"
            },
            {
               "id":"pair_dd3a015f4b2143bc8ec7149cf9f31e36",
               "name":"Authorization",
               "value":"{% response 'body', 'req_108b6d87926b4a1da95a1393d138ce93', 'b64::JC5BdXRoZW50aWNhdGlvblJlc3VsdC5JZFRva2Vu::46b', 'when-expired', 3000 %}",
               "description":""
            }
         ],
         "authentication":{
            
         },
         "metaSortKey":-1643625554617.75,
         "isPrivate":false,
         "settingStoreCookies":true,
         "settingSendCookies":true,
         "settingDisableRenderRequestBody":false,
         "settingEncodeUrl":true,
         "settingRebuildPath":true,
         "settingFollowRedirects":"global",
         "_type":"request"
      },
      {
         "_id":"req_445592d5a08d447ca140fa14f27cb9ef",
         "parentId":"wrk_4a5a7b0f3f1d40898c0652e42004d10c",
         "modified":1657573696696,
         "created":1643638194972,
         "url":"{{ _.graphql }}",
         "name":"Deploy Plan",
         "description":"",
         "method":"POST",
         "body":{
            "mimeType":"application/graphql",
            "text":"{\"query\":\"mutation DeployPlan {\\n\\tdeployPlan(\\n\\t\\tinput: {\\n\\t\\t\\tplanVersionId: \\\"{{ _.versionId }}\\\"\\n\\t\\t\\tproviderId: \\\"{{ _.providerId }}\\\"\\n\\t\\t}\\n\\t) {\\n\\t\\t... on PlanVersionWrongTransition {\\n\\t\\t\\terrorMessage\\n\\t\\t\\tproviderId\\n\\t\\t\\tplanVersionId\\n\\t\\t\\terrorCode\\n\\t\\t}\\n\\t\\t... on PlanVersionPayload {\\n\\t\\t\\t__typename\\n\\t\\t\\tplanVersion {\\n\\t\\t\\t\\tversion\\n\\t\\t\\t\\tstate\\n\\t\\t\\t\\tid\\n\\t\\t\\t\\tplanServices {\\n\\t\\t\\t\\t\\tbalanceName\\n\\t\\t\\t\\t\\tid\\n\\t\\t\\t\\t\\tname\\n\\t\\t\\t\\t\\tratingGroupId\\n\\t\\t\\t\\t}\\n\\t\\t\\t\\tplan {\\n\\t\\t\\t\\t\\tid\\n\\t\\t\\t\\t\\tname\\n\\t\\t\\t\\t}\\n\\t\\t\\t}\\n\\t\\t}\\n\\t\\t... on MigrationAlreadyInProgress {\\n\\t\\t\\terrorMessage\\n\\t\\t\\tproviderId\\n\\t\\t\\tplanVersionId\\n\\t\\t\\terrorCode\\n\\t\\t}\\n\\t\\t... on DeploymentVerificationFailed {\\n\\t\\t\\terrorMessage\\n\\t\\t\\tplanVersionId\\n\\t\\t\\tproviderId\\n\\t\\t\\terrorCode\\n\\t\\t}\\n\\t\\t... on PlanVersionNotFound {\\n\\t\\t\\terrorMessage\\n\\t\\t\\tproviderId\\n\\t\\t\\tplanVersionId\\n\\t\\t\\terrorCode\\n\\t\\t}\\n\\t}\\n}\\n\",\"operationName\":\"DeployPlan\"}"
         },
         "parameters":[
            
         ],
         "headers":[
            {
               "name":"Content-Type",
               "value":"application/json",
               "id":"pair_cd7dc08d0e25421b85e4e0a45aafa0fc"
            },
            {
               "id":"pair_65176a925dd247b7b609ec8811a0d2ac",
               "name":"Authorization",
               "value":"{% response 'body', 'req_108b6d87926b4a1da95a1393d138ce93', 'b64::JC5BdXRoZW50aWNhdGlvblJlc3VsdC5JZFRva2Vu::46b', 'when-expired', 3000 %}",
               "description":""
            }
         ],
         "authentication":{
            
         },
         "metaSortKey":-1643624348699.875,
         "isPrivate":false,
         "settingStoreCookies":true,
         "settingSendCookies":true,
         "settingDisableRenderRequestBody":false,
         "settingEncodeUrl":true,
         "settingRebuildPath":true,
         "settingFollowRedirects":"global",
         "_type":"request"
      },
      {
         "_id":"req_6f0543cc1c3b4d0e9b033359ef64ea44",
         "parentId":"wrk_4a5a7b0f3f1d40898c0652e42004d10c",
         "modified":1657573697551,
         "created":1643638294618,
         "url":"{{ _.graphql }}",
         "name":"Make Plan Assignable",
         "description":"",
         "method":"POST",
         "body":{
            "mimeType":"application/graphql",
            "text":"{\"query\":\"mutation MakePlanAssignable {\\n\\tmakePlanAssignable(\\n\\t\\tinput: {\\n\\t\\t\\tplanVersionId: \\\"{{ _.versionId }}\\\"\\n\\t\\t\\tproviderId: \\\"{{ _.providerId }}\\\"\\n\\t\\t}\\n\\t) {\\n    ... on PlanVersionWrongTransition {\\n      errorMessage\\n      providerId\\n      planVersionId\\n      errorCode\\n    }\\n    ... on PlanVersionNotFound {\\n      errorMessage\\n      providerId\\n      planVersionId\\n      errorCode\\n    }\\n    ... on PlanVersionPayload {\\n      __typename\\n      planVersion {\\n        version\\n        state\\n        id\\n      }\\n    }\\n  }\\n}\\n\",\"operationName\":\"MakePlanAssignable\"}"
         },
         "parameters":[
            
         ],
         "headers":[
            {
               "name":"Content-Type",
               "value":"application/json",
               "id":"pair_1286fe3b252747a2879485fe4698e841"
            },
            {
               "id":"pair_47dd4f4bf7354ef4b2c6d13e891a17a3",
               "name":"Authorization",
               "value":"{% response 'body', 'req_108b6d87926b4a1da95a1393d138ce93', 'b64::JC5BdXRoZW50aWNhdGlvblJlc3VsdC5JZFRva2Vu::46b', 'when-expired', 3000 %}",
               "description":""
            }
         ],
         "authentication":{
            
         },
         "metaSortKey":-1643623745740.9375,
         "isPrivate":false,
         "settingStoreCookies":true,
         "settingSendCookies":true,
         "settingDisableRenderRequestBody":false,
         "settingEncodeUrl":true,
         "settingRebuildPath":true,
         "settingFollowRedirects":"global",
         "_type":"request"
      },
      {
         "_id":"req_8aab8fe927eb4bdf87acc78cd7bdfd1c",
         "parentId":"wrk_4a5a7b0f3f1d40898c0652e42004d10c",
         "modified":1657573689839,
         "created":1643647454094,
         "url":"{{ _.graphql }}",
         "name":"Make Plan Not Assignable",
         "description":"",
         "method":"POST",
         "body":{
            "mimeType":"application/graphql",
            "text":"{\"query\":\"mutation MakePlanNotAssignable {\\n\\tmakePlanNotAssignable(\\n\\t\\tinput: {\\n\\t\\t\\tproviderId: \\\"{{ _.providerId }}\\\"\\n\\t\\t\\tplanVersionId: \\\"{{ _.versionId }}\\\"\\n\\t\\t}\\n\\t) {\\n    ... on PlanVersionWrongTransition {\\n      errorMessage\\n      providerId\\n      planVersionId\\n      errorCode\\n    }\\n    ... on PlanVersionNotFound {\\n      errorMessage\\n      providerId\\n      planVersionId\\n      errorCode\\n    }\\n    ... on PlanVersionPayload {\\n      __typename\\n      planVersion {\\n        version\\n        state\\n        id\\n      }\\n    }\\n  }\\n}\\n\",\"operationName\":\"MakePlanNotAssignable\"}"
         },
         "parameters":[
            
         ],
         "headers":[
            {
               "name":"Content-Type",
               "value":"application/json",
               "id":"pair_dcd92df9146f4b8aad8257305b3e4a2b"
            },
            {
               "id":"pair_bd7d25f40ca9492c8e92e58c6d9ce5d6",
               "name":"Authorization",
               "value":"{% response 'body', 'req_108b6d87926b4a1da95a1393d138ce93', 'b64::JC5BdXRoZW50aWNhdGlvblJlc3VsdC5JZFRva2Vu::46b', 'when-expired', 3000 %}",
               "description":""
            }
         ],
         "authentication":{
            
         },
         "metaSortKey":-1643623444261.4688,
         "isPrivate":false,
         "settingStoreCookies":true,
         "settingSendCookies":true,
         "settingDisableRenderRequestBody":false,
         "settingEncodeUrl":true,
         "settingRebuildPath":true,
         "settingFollowRedirects":"global",
         "_type":"request"
      },
      {
         "_id":"req_5f7c27e2900f4c59a7de414ea807cb86",
         "parentId":"wrk_4a5a7b0f3f1d40898c0652e42004d10c",
         "modified":1657573677256,
         "created":1643648242117,
         "url":"{{ _.graphql }}",
         "name":"Subscribe To Plan",
         "description":"",
         "method":"POST",
         "body":{
            "mimeType":"application/graphql",
            "text":"{\"query\":\"mutation SubscribeToPlan {\\n\\tsubscribeToPlan(\\n\\t\\tinput: {\\n\\t\\t\\taccountId: \\\"{{ _.accountId }}\\\"\\n\\t\\t\\tproviderId: \\\"{{ _.providerId }}\\\"\\n\\t\\t\\tplanVersionId: \\\"{{ _.versionId }}\\\"\\n\\t\\t}\\n\\t) {\\n    ... on SubscribeToPlanVersionValidationFailed {\\n      errorMessage\\n      errorCode\\n    }\\n    ... on InvalidField {\\n      errorMessage\\n      fieldName\\n      errorCode\\n    }\\n    ... on AccountNotFound {\\n      errorMessage\\n      providerId\\n      errorCode\\n      accountId\\n    }\\n    ... on PlanVersionIsNotAssignable {\\n      errorMessage\\n      providerId\\n      planVersionId\\n      errorCode\\n    }\\n    ... on PlanVersionNotFound {\\n      errorMessage\\n      planVersionId\\n      providerId\\n      errorCode\\n    }\\n    ... on SubscribeToPlanVersionPayload {\\n      __typename\\n      subscribedPlanVersion {\\n        to\\n        from\\n        planVersion {\\n          version\\n          state\\n          id\\n        }\\n      }\\n      account {\\n        customData\\n        id\\n        activePlanVersions {\\n          from\\n          to\\n          planVersion {\\n            version\\n            state\\n            id\\n          }\\n        }\\n        archivedPlanVersions {\\n          to\\n          from\\n          planVersion {\\n            version\\n            state\\n            id\\n          }\\n        }\\n        balance {\\n          version\\n          value\\n          customData\\n        }\\n        inactivePlanVersions {\\n          to\\n          planVersion {\\n            state\\n            version\\n            id\\n          }\\n          from\\n        }\\n      }\\n    }\\n  }\\n}\\n\",\"operationName\":\"SubscribeToPlan\"}"
         },
         "parameters":[
            
         ],
         "headers":[
            {
               "name":"Content-Type",
               "value":"application/json",
               "id":"pair_a033145678994a06b6e0bcbc2e9e0db5"
            },
            {
               "id":"pair_683047c7214a41a59e9b93026a6d2b70",
               "name":"Authorization",
               "value":"{% response 'body', 'req_76f28bad434041c78a1d8e79c9fc80a8', 'b64::JC5BdXRoZW50aWNhdGlvblJlc3VsdC5JZFRva2Vu::46b', 'when-expired', 3000 %}",
               "description":""
            }
         ],
         "authentication":{
            
         },
         "metaSortKey":-1643623368891.6016,
         "isPrivate":false,
         "settingStoreCookies":true,
         "settingSendCookies":true,
         "settingDisableRenderRequestBody":false,
         "settingEncodeUrl":true,
         "settingRebuildPath":true,
         "settingFollowRedirects":"global",
         "_type":"request"
      },
      {
         "_id":"req_de5a51ca1fe442c3bbdd8c97ed1b00cd",
         "parentId":"wrk_4a5a7b0f3f1d40898c0652e42004d10c",
         "modified":1657573637334,
         "created":1643648325705,
         "url":"{{ _.graphql }}",
         "name":"Cancel Plan Subscription",
         "description":"",
         "method":"POST",
         "body":{
            "mimeType":"application/graphql",
            "text":"{\"query\":\"mutation CancelPlanSubscription {\\n\\tcancelPlanSubscription(\\n\\t\\tinput: {\\n\\t\\t\\taccountId: \\\"{{ _.accountId }}\\\"\\n\\t\\t\\tproviderId: \\\"{{ _.providerId }}\\\"\\n\\t\\t\\tplanVersionId: \\\"{{ _.versionId }}\\\"\\n\\t\\t}\\n\\t) {\\n\\t\\t... on SubscriptionNotFound {\\n\\t\\t\\tfrom\\n\\t\\t\\tto\\n\\t\\t\\tplanVersionId\\n\\t\\t\\terrorMessage\\n\\t\\t\\terrorCode\\n\\t\\t}\\n\\t\\t... on InvalidField {\\n\\t\\t\\terrorMessage\\n\\t\\t\\tfieldName\\n\\t\\t\\terrorCode\\n\\t\\t}\\n\\t\\t... on AccountNotFound {\\n\\t\\t\\terrorMessage\\n\\t\\t\\tproviderId\\n\\t\\t\\terrorCode\\n\\t\\t\\taccountId\\n\\t\\t}\\n\\t\\t... on PlanVersionNotFound {\\n\\t\\t\\tproviderId\\n\\t\\t\\tplanVersionId\\n\\t\\t\\terrorMessage\\n\\t\\t\\terrorCode\\n\\t\\t}\\n\\t\\t... on CancelPlanVersionSubscriptionPayload {\\n\\t\\t\\t__typename\\n\\t\\t\\taccount {\\n\\t\\t\\t\\tproviderId\\n\\t\\t\\t\\tid\\n\\t\\t\\t\\tcustomData\\n\\t\\t\\t\\tactivePlanVersions {\\n\\t\\t\\t\\t\\tto\\n\\t\\t\\t\\t\\tfrom\\n\\t\\t\\t\\t\\tplanVersion {\\n\\t\\t\\t\\t\\t\\tversion\\n\\t\\t\\t\\t\\t\\tstate\\n\\t\\t\\t\\t\\t\\tid\\n\\t\\t\\t\\t\\t}\\n\\t\\t\\t\\t}\\n\\t\\t\\t\\tarchivedPlanVersions {\\n\\t\\t\\t\\t\\tto\\n\\t\\t\\t\\t\\tfrom\\n\\t\\t\\t\\t\\tplanVersion {\\n\\t\\t\\t\\t\\t\\tversion\\n\\t\\t\\t\\t\\t\\tstate\\n\\t\\t\\t\\t\\t\\tid\\n\\t\\t\\t\\t\\t}\\n\\t\\t\\t\\t}\\n\\t\\t\\t\\tinactivePlanVersions {\\n\\t\\t\\t\\t\\tto\\n\\t\\t\\t\\t\\tfrom\\n\\t\\t\\t\\t\\tplanVersion {\\n\\t\\t\\t\\t\\t\\tversion\\n\\t\\t\\t\\t\\t\\tstate\\n\\t\\t\\t\\t\\t\\tid\\n\\t\\t\\t\\t\\t}\\n\\t\\t\\t\\t}\\n\\t\\t\\t}\\n\\t\\t}\\n\\t}\\n}\\n\",\"operationName\":\"CancelPlanSubscription\"}"
         },
         "parameters":[
            
         ],
         "headers":[
            {
               "name":"Content-Type",
               "value":"application/json",
               "id":"pair_d56c0d2db718476e842baed987aa8626"
            },
            {
               "id":"pair_eda8c7f23ab64a05aa69308d63113488",
               "name":"Authorization",
               "value":"{% response 'body', 'req_76f28bad434041c78a1d8e79c9fc80a8', 'b64::JC5BdXRoZW50aWNhdGlvblJlc3VsdC5JZFRva2Vu::46b', 'when-expired', 3000 %}",
               "description":""
            }
         ],
         "authentication":{
            
         },
         "metaSortKey":-1643623331206.668,
         "isPrivate":false,
         "settingStoreCookies":true,
         "settingSendCookies":true,
         "settingDisableRenderRequestBody":false,
         "settingEncodeUrl":true,
         "settingRebuildPath":true,
         "settingFollowRedirects":"global",
         "_type":"request"
      },
      {
         "_id":"req_43ac3890a71c4fd099ad206633ad31ff",
         "parentId":"wrk_4a5a7b0f3f1d40898c0652e42004d10c",
         "modified":1657573634703,
         "created":1643647508774,
         "url":"{{ _.graphql }}",
         "name":"Archive plan version",
         "description":"",
         "method":"POST",
         "body":{
            "mimeType":"application/graphql",
            "text":"{\"query\":\"mutation ArchivePlanVersion {\\n\\tarchivePlanVersion(\\n\\t\\tinput: {\\n\\t\\t\\tproviderId: \\\"{{ _.providerId }}\\\"\\n\\t\\t\\tplanVersionId: \\\"{{ _.versionId }}\\\"\\n\\t\\t}\\n\\t) {\\n    ... on PlanVersionWrongTransition {\\n      errorMessage\\n      providerId\\n      planVersionId\\n      errorCode\\n    }\\n    ... on PlanVersionNotFound {\\n      errorMessage\\n      providerId\\n      planVersionId\\n      errorCode\\n    }\\n    ... on ArchivePlanVersionPayload {\\n      __typename\\n      archivedPlanVersion {\\n        version\\n        state\\n        id\\n      }\\n    }\\n  }\\n}\\n\",\"operationName\":\"ArchivePlanVersion\"}"
         },
         "parameters":[
            
         ],
         "headers":[
            {
               "name":"Content-Type",
               "value":"application/json",
               "id":"pair_96be7eda066741238e7c2a071d2372aa"
            },
            {
               "id":"pair_0747c6fa872b4055ba9abb1c05caa612",
               "name":"Authorization",
               "value":"{% response 'body', 'req_108b6d87926b4a1da95a1393d138ce93', 'b64::JC5BdXRoZW50aWNhdGlvblJlc3VsdC5JZFRva2Vu::46b', 'when-expired', 3000 %}",
               "description":""
            }
         ],
         "authentication":{
            
         },
         "metaSortKey":-1643623293521.7344,
         "isPrivate":false,
         "settingStoreCookies":true,
         "settingSendCookies":true,
         "settingDisableRenderRequestBody":false,
         "settingEncodeUrl":true,
         "settingRebuildPath":true,
         "settingFollowRedirects":"global",
         "_type":"request"
      },
      {
         "_id":"req_c855e513bd4f4c9c8cf3c4c768527ae0",
         "parentId":"wrk_4a5a7b0f3f1d40898c0652e42004d10c",
         "modified":1657573631451,
         "created":1643623142782,
         "url":"{{ _.elb }}nchf-convergedcharging/v3/chargingData",
         "name":"Credit Request 5G",
         "description":"",
         "method":"POST",
         "body":{
            "mimeType":"application/json",
            "text":"{\n\t\"invocationSequenceNumber\": 1,\n\t\"tenantIdentifier\": \"{{ _.providerId }}\",\n\t\"subscriberIdentifier\": \"{{ _.deviceId }}\",\n\t\"multipleUnitUsage\": [\n\t\t{\n\t\t\t\"requestedUnit\": {\n\t\t\t\t\"serviceSpecificUnits\": 1000\n\t\t\t},\n\t\t\t\"ratingGroup\": 400\n\t\t}\n\t],\n\t\"oneTimeEvent\": true,\n\t\"oneTimeEventType\": \"IEC\",\n\t\"requestedAction\": \"TOP_UP\",\n\t\"nfConsumerIdentification\": {\n\t\t\"nodeFunctionality\": \"SMF\"\n\t},\n\t\"invocationTimeStamp\": \"{% now 'iso-8601', '' %}\"\n}"
         },
         "parameters":[
            
         ],
         "headers":[
            {
               "id":"pair_d0c9b566bb5847feb084cc6cead54da8",
               "name":"Content-Type",
               "value":"application/json",
               "description":""
            },
            {
               "id":"pair_80000060ccc643b8a70fb145352be2f3",
               "name":"Authorization",
               "value":"Bearer {% response 'body', 'req_b21810c7581c49cc9dd3791e4ccc1060', 'b64::JC5BdXRoZW50aWNhdGlvblJlc3VsdC5JZFRva2Vu::46b', 'when-expired', 3000 %}",
               "description":""
            }
         ],
         "authentication":{
            
         },
         "metaSortKey":-1643623142782,
         "isPrivate":false,
         "settingStoreCookies":true,
         "settingSendCookies":true,
         "settingDisableRenderRequestBody":false,
         "settingEncodeUrl":true,
         "settingRebuildPath":true,
         "settingFollowRedirects":"global",
         "_type":"request"
      },
      {
         "_id":"req_e94c78d438e249a2aaf90440c655419b",
         "parentId":"wrk_4a5a7b0f3f1d40898c0652e42004d10c",
         "modified":1657573625026,
         "created":1643703946137,
         "url":"{{ _.elb }}nchf-convergedcharging/v3/chargingData",
         "name":"Charge Request 5G",
         "description":"",
         "method":"POST",
         "body":{
            "mimeType":"application/json",
            "text":"{\n\t\"invocationSequenceNumber\": 1,\n\t\"tenantIdentifier\": \"{{ _.providerId }}\",\n\t\"subscriberIdentifier\": \"{{ _.deviceId }}\",\n\t\"multipleUnitUsage\": [\n\t\t{\n\t\t\t\"requestedUnit\": {\n\t\t\t\t\"time\": 300\n\t\t\t},\n\t\t\t\"ratingGroup\": 100\n\t\t}\n\t],\n\t\"locationReportingChargingInformation\": {\n\t\t\"pSCellInformation\": {\n\t\t\t\"nrcgi\": {\n\t\t\t\t\"nrCellId\": \"11\",\n\t\t\t\t\"nid\": \"12\",\n\t\t\t\t\"plmnId\": {\n\t\t\t\t\t\"mcc\": \"310\",\n\t\t\t\t\t\"mnc\": \"005\"\n\t\t\t\t}\n\t\t\t}\n\t\t}\n\t},\n\t\"nfConsumerIdentification\": {\n\t\t\"nodeFunctionality\": \"SMF\"\n\t},\n\t\"invocationTimeStamp\": \"{% now 'iso-8601', '' %}\"\n}\n"
         },
         "parameters":[
            
         ],
         "headers":[
            {
               "id":"pair_d0c9b566bb5847feb084cc6cead54da8",
               "name":"Content-Type",
               "value":"application/json",
               "description":""
            },
            {
               "id":"pair_80000060ccc643b8a70fb145352be2f3",
               "name":"Authorization",
               "value":"Bearer {% response 'body', 'req_b21810c7581c49cc9dd3791e4ccc1060', 'b64::JC5BdXRoZW50aWNhdGlvblJlc3VsdC5JZFRva2Vu::46b', 'when-expired', 3000 %}",
               "description":""
            }
         ],
         "authentication":{
            
         },
         "metaSortKey":-1643623142744.5,
         "isPrivate":false,
         "settingStoreCookies":true,
         "settingSendCookies":true,
         "settingDisableRenderRequestBody":false,
         "settingEncodeUrl":true,
         "settingRebuildPath":true,
         "settingFollowRedirects":"global",
         "_type":"request"
      },
      {
         "_id":"req_1cad1b643fa5459d9786b56f67ee8a83",
         "parentId":"wrk_4a5a7b0f3f1d40898c0652e42004d10c",
         "modified":1657573610107,
         "created":1652738335924,
         "url":"{{ _.elb }}nchf-convergedcharging/v3/chargingData/{% response 'header', 'req_e94c78d438e249a2aaf90440c655419b', 'b64::bG9jYXRpb24=::46b', 'never', 60 %}/update",
         "name":"Charge Request 5G Update",
         "description":"",
         "method":"POST",
         "body":{
            "mimeType":"application/json",
            "text":"{\n\t\"invocationSequenceNumber\": 2,\n\t\"tenantIdentifier\": \"{{ _.providerId }}\",\n\t\"subscriberIdentifier\": \"{{ _.deviceId }}\",\n\t\"multipleUnitUsage\": [\n\t\t{\n\t\t\t\"requestedUnit\": {\n\t\t\t\t\"time\": 0\n\t\t\t},\n\t\t\t\"usedUnitContainer\": [\n\t\t\t\t{\n\t\t\t\t\t\"localSequenceNumber\": 1,\n\t\t\t\t\t\"time\": 300\n\t\t\t\t}\n\t\t\t],\n\t\t\t\"ratingGroup\": 100\n\t\t}\n\t],\n\t\"locationReportingChargingInformation\": {\n\t\t\"pSCellInformation\": {\n\t\t\t\"nrcgi\": {\n\t\t\t\t\"nrCellId\": \"11\",\n\t\t\t\t\"nid\": \"12\",\n\t\t\t\t\"plmnId\": {\n\t\t\t\t\t\"mcc\": \"310\",\n\t\t\t\t\t\"mnc\": \"170\"\n\t\t\t\t}\n\t\t\t}\n\t\t}\n\t},\n\t\"nfConsumerIdentification\": {\n\t\t\"nodeFunctionality\": \"SMF\"\n\t},\n\t\"invocationTimeStamp\": \"{% now 'iso-8601', '' %}\"\n}"
         },
         "parameters":[
            
         ],
         "headers":[
            {
               "id":"pair_d0c9b566bb5847feb084cc6cead54da8",
               "name":"Content-Type",
               "value":"application/json",
               "description":""
            },
            {
               "id":"pair_80000060ccc643b8a70fb145352be2f3",
               "name":"Authorization",
               "value":"Bearer {% response 'body', 'req_b21810c7581c49cc9dd3791e4ccc1060', 'b64::JC5BdXRoZW50aWNhdGlvblJlc3VsdC5JZFRva2Vu::46b', 'when-expired', 3000 %}",
               "description":""
            }
         ],
         "authentication":{
            
         },
         "metaSortKey":-1643623142719.5,
         "isPrivate":false,
         "settingStoreCookies":true,
         "settingSendCookies":true,
         "settingDisableRenderRequestBody":false,
         "settingEncodeUrl":true,
         "settingRebuildPath":true,
         "settingFollowRedirects":"global",
         "_type":"request"
      },
      {
         "_id":"req_07a5bcb6cfac4344aacabd18ae34aef0",
         "parentId":"wrk_4a5a7b0f3f1d40898c0652e42004d10c",
         "modified":1657573615494,
         "created":1652738343220,
         "url":"{{ _.elb }}nchf-convergedcharging/v3/chargingData/{% response 'header', 'req_e94c78d438e249a2aaf90440c655419b', 'b64::bG9jYXRpb24=::46b', 'never', 60 %}/release",
         "name":"Charge Request 5G Terminate",
         "description":"",
         "method":"POST",
         "body":{
            "mimeType":"application/json",
            "text":"{\n\t\"invocationSequenceNumber\": 3,\n\t\"tenantIdentifier\": \"{{ _.providerId }}\",\n\t\"subscriberIdentifier\": \"{{ _.deviceId }}\",\n\t\"multipleUnitUsage\": [\n\t\t{\n\t\t\t\"usedUnitContainer\": [\n\t\t\t\t{\n\t\t\t\t\t\"localSequenceNumber\": 1,\n\t\t\t\t\t\"time\": 0\n\t\t\t\t}\n\t\t\t],\n\t\t\t\"ratingGroup\": 100\n\t\t}\n\t],\n\t\"locationReportingChargingInformation\": {\n\t\t\"pSCellInformation\": {\n\t\t\t\"nrcgi\": {\n\t\t\t\t\"nrCellId\": \"11\",\n\t\t\t\t\"nid\": \"12\",\n\t\t\t\t\"plmnId\": {\n\t\t\t\t\t\"mcc\": \"310\",\n\t\t\t\t\t\"mnc\": \"170\"\n\t\t\t\t}\n\t\t\t}\n\t\t}\n\t},\n\t\"nfConsumerIdentification\": {\n\t\t\"nodeFunctionality\": \"SMF\"\n\t},\n\t\"invocationTimeStamp\": \"{% now 'iso-8601', '' %}\"\n}"
         },
         "parameters":[
            
         ],
         "headers":[
            {
               "id":"pair_d0c9b566bb5847feb084cc6cead54da8",
               "name":"Content-Type",
               "value":"application/json",
               "description":""
            },
            {
               "id":"pair_80000060ccc643b8a70fb145352be2f3",
               "name":"Authorization",
               "value":"Bearer {% response 'body', 'req_b21810c7581c49cc9dd3791e4ccc1060', 'b64::JC5BdXRoZW50aWNhdGlvblJlc3VsdC5JZFRva2Vu::46b', 'when-expired', 3000 %}",
               "description":""
            },
            {
               "id":"pair_7066c7d34ced4f60bc9022f2fed1d90f",
               "name":"",
               "value":"",
               "description":""
            }
         ],
         "authentication":{
            
         },
         "metaSortKey":-1643623142713.25,
         "isPrivate":false,
         "settingStoreCookies":true,
         "settingSendCookies":true,
         "settingDisableRenderRequestBody":false,
         "settingEncodeUrl":true,
         "settingRebuildPath":true,
         "settingFollowRedirects":"global",
         "_type":"request"
      },
      {
         "_id":"req_1f5c78d9e0564630a5efa1a2b51d59e3",
         "parentId":"wrk_4a5a7b0f3f1d40898c0652e42004d10c",
         "modified":1657573570086,
         "created":1653489083602,
         "url":"{{ _.graphql }}",
         "name":"getEventDataRecordByDevice",
         "description":"",
         "method":"POST",
         "body":{
            "mimeType":"application/graphql",
            "text":"{\"query\":\"query {\\n    getEventDataRecordsByDevice(providerId: \\\"{{ _.providerId }}\\\", deviceId: \\\"{{ _.deviceId }}\\\",first: 10, filterBy: {types: [BILLING,CHARGING], from: \\\"2022-06-16T00:00:59.954Z\\\", to:\\\"2022-06-18T01:59:59.954Z\\\"}){\\n        ... on EventDataRecordDeviceConnection{\\n            edges{\\n                node{\\n                    createdAt\\n                    customData\\n                    id\\n                }\\n                cursor\\n            }\\n            pageInfo{\\n            hasPreviousPage\\n            hasNextPage\\n            startCursor\\n            endCursor\\n            }\\n        }\\n        ... on DeviceNotFound{\\n            providerId\\n            deviceId\\n            errorCode\\n            errorMessage\\n        }\\n    }\\n}\"}"
         },
         "parameters":[
            
         ],
         "headers":[
            {
               "id":"pair_acb1f08d07784d078d0787ded095f8f9",
               "name":"Content-Type",
               "value":"application/json",
               "description":"",
               "disabled":true
            },
            {
               "id":"pair_6cae1033c4d24489b76e02ce66fb5b71",
               "name":"Authorization",
               "value":"{% response 'body', 'req_76f28bad434041c78a1d8e79c9fc80a8', 'b64::JC5BdXRoZW50aWNhdGlvblJlc3VsdC5JZFRva2Vu::46b', 'when-expired', 300 %}",
               "description":""
            }
         ],
         "authentication":{
            
         },
         "metaSortKey":-1643623142669.5,
         "isPrivate":false,
         "settingStoreCookies":true,
         "settingSendCookies":true,
         "settingDisableRenderRequestBody":false,
         "settingEncodeUrl":true,
         "settingRebuildPath":true,
         "settingFollowRedirects":"global",
         "_type":"request"
      },
      {
         "_id":"req_20c553657f5a48c2b9deb435f5aad354",
         "parentId":"wrk_4a5a7b0f3f1d40898c0652e42004d10c",
         "modified":1657573568445,
         "created":1655302281914,
         "url":"{{ _.graphql }}",
         "name":"getEventDataRecordByAccount",
         "description":"",
         "method":"POST",
         "body":{
            "mimeType":"application/graphql",
            "text":"{\"query\":\"query {\\n    getEventDataRecordsByAccount(providerId: \\\"{{ _.providerId }}\\\", accountId: \\\"{{ _.accountId }}\\\",first: 10, filterBy: {types: [BILLING,CHARGING], from: \\\"2022-06-08T00:00:59.954Z\\\", to:\\\"2022-06-08T01:59:59.954Z\\\"}){\\n        ... on EventDataRecordAccountConnection{\\n             account{\\n                providerId\\n                customData\\n                balance{\\n                    version\\n                    value\\n                    customData\\n                }\\n            }\\n\\t\\t\\t\\t\\t  edges{\\n                node{\\n                    createdAt\\n                    customData\\n                    id\\n                }\\n                cursor\\n            }\\n            pageInfo{\\n            hasPreviousPage\\n            hasNextPage\\n            startCursor\\n            endCursor\\n            }\\n        }\\n        ... on AccountNotFound{\\n            providerId\\n            accountId\\n            errorCode\\n            errorMessage\\n        }\\n    }\\n}\"}"
         },
         "parameters":[
            
         ],
         "headers":[
            {
               "id":"pair_acb1f08d07784d078d0787ded095f8f9",
               "name":"Content-Type",
               "value":"application/json",
               "description":"",
               "disabled":true
            },
            {
               "id":"pair_6cae1033c4d24489b76e02ce66fb5b71",
               "name":"Authorization",
               "value":"{% response 'body', 'req_76f28bad434041c78a1d8e79c9fc80a8', 'b64::JC5BdXRoZW50aWNhdGlvblJlc3VsdC5JZFRva2Vu::46b', 'when-expired', 300 %}",
               "description":""
            }
         ],
         "authentication":{
            
         },
         "metaSortKey":-1643623142663.25,
         "isPrivate":false,
         "settingStoreCookies":true,
         "settingSendCookies":true,
         "settingDisableRenderRequestBody":false,
         "settingEncodeUrl":true,
         "settingRebuildPath":true,
         "settingFollowRedirects":"global",
         "_type":"request"
      },
      {
         "_id":"req_8e2c868fdb6948a7be2f4eb7cc39abc1",
         "parentId":"wrk_4a5a7b0f3f1d40898c0652e42004d10c",
         "modified":1657573534250,
         "created":1652449043347,
         "url":"{{ _.graphql }}",
         "name":"Create field mapping",
         "description":"",
         "method":"POST",
         "body":{
            "mimeType":"application/graphql",
            "text":"{\"query\":\"mutation CreateFieldMapping {\\n\\tcreateFieldMapping(\\n\\t\\tinput: {\\n\\t\\t\\tpath: \\\"transformedRequest.multipleUnitUsage[].ratingGroup\\\"\\n\\t\\t\\texpr: \\\"\\\"\\n\\t\\t\\tproviderId: \\\"{{ _.providerId }}\\\"\\n\\t\\t}\\n\\t) {\\n\\t\\t... on CreateFieldMappingPayload {\\n\\t\\t\\t__typename\\n\\t\\t\\tfieldMapping {\\n\\t\\t\\t\\texpr\\n\\t\\t\\t\\tpath\\n\\t\\t\\t}\\n\\t\\t}\\n\\t\\t... on InvalidField {\\n\\t\\t\\terrorMessage\\n\\t\\t\\terrorCode\\n\\t\\t\\tfieldName\\n\\t\\t}\\n\\t\\t... on FieldMappingAlreadyExists {\\n\\t\\t\\terrorMessage\\n\\t\\t}\\n\\t}\\n}\\n\",\"operationName\":\"CreateFieldMapping\"}"
         },
         "parameters":[
            
         ],
         "headers":[
            {
               "name":"Content-Type",
               "value":"application/json",
               "id":"pair_fccdc91d042c489f989a64df5c832664"
            },
            {
               "id":"pair_9174c34c090f451ca07b268a1a9d64ec",
               "name":"Authorization",
               "value":"{% response 'body', 'req_108b6d87926b4a1da95a1393d138ce93', 'b64::JC5BdXRoZW50aWNhdGlvblJlc3VsdC5JZFRva2Vu::46b', 'when-expired', 3000 %}",
               "description":""
            }
         ],
         "authentication":{
            
         },
         "metaSortKey":-1643623142557,
         "isPrivate":false,
         "settingStoreCookies":true,
         "settingSendCookies":true,
         "settingDisableRenderRequestBody":false,
         "settingEncodeUrl":true,
         "settingRebuildPath":true,
         "settingFollowRedirects":"global",
         "_type":"request"
      },
      {
         "_id":"req_d69e9b21d7f043dfad634e8e6d5a0e23",
         "parentId":"wrk_4a5a7b0f3f1d40898c0652e42004d10c",
         "modified":1657573529507,
         "created":1652449083821,
         "url":"{{ _.graphql }}",
         "name":"Delete field mapping",
         "description":"",
         "method":"POST",
         "body":{
            "mimeType":"application/graphql",
            "text":"{\"query\":\"mutation DeleteFieldMapping {\\n\\tdeleteFieldMapping(input: { path: \\\"\\\", providerId: \\\"{{ _.providerId }}\\\" }) {\\n\\t\\t... on DeleteFieldMappingPayload {\\n\\t\\t\\t__typename\\n\\t\\t\\tdeletedPath\\n\\t\\t}\\n\\t\\t... on FieldMappingNotFound {\\n\\t\\t\\terrorMessage\\n\\t\\t\\terrorCode\\n\\t\\t\\tpath\\n\\t\\t\\tproviderId\\n\\t\\t}\\n\\t\\t... on FieldMappingHasReferences {\\n\\t\\t\\terrorMessage\\n\\t\\t\\terrorCode\\n\\t\\t}\\n\\t}\\n}\\n\",\"operationName\":\"DeleteFieldMapping\"}"
         },
         "parameters":[
            
         ],
         "headers":[
            {
               "name":"Content-Type",
               "value":"application/json",
               "id":"pair_fccdc91d042c489f989a64df5c832664"
            },
            {
               "id":"pair_9174c34c090f451ca07b268a1a9d64ec",
               "name":"Authorization",
               "value":"{% response 'body', 'req_108b6d87926b4a1da95a1393d138ce93', 'b64::JC5BdXRoZW50aWNhdGlvblJlc3VsdC5JZFRva2Vu::46b', 'when-expired', 3000 %}",
               "description":""
            }
         ],
         "authentication":{
            
         },
         "metaSortKey":-1643623142544.5,
         "isPrivate":false,
         "settingStoreCookies":true,
         "settingSendCookies":true,
         "settingDisableRenderRequestBody":false,
         "settingEncodeUrl":true,
         "settingRebuildPath":true,
         "settingFollowRedirects":"global",
         "_type":"request"
      },
      {
         "_id":"req_ce8763a622d64b55b819d0dbb2a64615",
         "parentId":"wrk_4a5a7b0f3f1d40898c0652e42004d10c",
         "modified":1657573525594,
         "created":1652449139619,
         "url":"{{ _.graphql }}",
         "name":"Deploy field mapping",
         "description":"",
         "method":"POST",
         "body":{
            "mimeType":"application/graphql",
            "text":"{\"query\":\"mutation DeployFieldMappings {\\n\\tdeployFieldMappings(\\n\\t\\tinput: {\\n\\t\\t\\tproviderId: \\\"{{ _.providerId }}\\\"\\n\\t\\t}\\n\\t) {\\n\\t\\t... on DeployFieldMappingsPayload {\\n\\t\\t\\t__typename\\n\\t\\t\\tdeployedFieldMapping {\\n\\t\\t\\t\\tfrom\\n\\t\\t\\t\\tproviderId\\n\\t\\t\\t\\tfieldMappings(first: 10) {\\n\\t\\t\\t\\t\\tedges {\\n\\t\\t\\t\\t\\t\\tnode {\\n\\t\\t\\t\\t\\t\\t\\texpr\\n\\t\\t\\t\\t\\t\\t\\tpath\\n\\t\\t\\t\\t\\t\\t}\\n\\t\\t\\t\\t\\t}\\n\\t\\t\\t\\t}\\n\\t\\t\\t}\\n\\t\\t}\\n\\t\\t... on FieldMappingNotFound {\\n\\t\\t\\terrorMessage\\n\\t\\t\\terrorCode\\n\\t\\t\\tpath\\n\\t\\t\\tproviderId\\n\\t\\t}\\n\\t\\t... on InvalidField {\\n\\t\\t\\terrorMessage\\n\\t\\t\\terrorCode\\n\\t\\t\\tfieldName\\n\\t\\t}\\n\\t}\\n}\\n\",\"operationName\":\"DeployFieldMappings\"}"
         },
         "parameters":[
            
         ],
         "headers":[
            {
               "name":"Content-Type",
               "value":"application/json",
               "id":"pair_fccdc91d042c489f989a64df5c832664"
            },
            {
               "id":"pair_9174c34c090f451ca07b268a1a9d64ec",
               "name":"Authorization",
               "value":"{% response 'body', 'req_108b6d87926b4a1da95a1393d138ce93', 'b64::JC5BdXRoZW50aWNhdGlvblJlc3VsdC5JZFRva2Vu::46b', 'when-expired', 3000 %}",
               "description":""
            }
         ],
         "authentication":{
            
         },
         "metaSortKey":-1643623142538.25,
         "isPrivate":false,
         "settingStoreCookies":true,
         "settingSendCookies":true,
         "settingDisableRenderRequestBody":false,
         "settingEncodeUrl":true,
         "settingRebuildPath":true,
         "settingFollowRedirects":"global",
         "_type":"request"
      },
      {
         "_id":"req_a0b8be1f93df40ec980dcff46786e5a9",
         "parentId":"wrk_4a5a7b0f3f1d40898c0652e42004d10c",
         "modified":1657573498609,
         "created":1652449174830,
         "url":"{{ _.graphql }}",
         "name":"Update field mapping",
         "description":"",
         "method":"POST",
         "body":{
            "mimeType":"application/graphql",
            "text":"{\"query\":\"mutation UpdateFieldMapping {\\n\\tupdateFieldMapping(\\n\\t\\tinput: { expr: \\\"\\\", path: \\\"\\\", providerId: \\\"{{ _.providerId }}\\\" }\\n\\t) {\\n\\t\\t... on UpdateFieldMappingPayload {\\n\\t\\t\\t__typename\\n\\t\\t\\tfieldMapping {\\n\\t\\t\\t\\texpr\\n\\t\\t\\t\\tpath\\n\\t\\t\\t}\\n\\t\\t}\\n\\t\\t... on FieldMappingNotFound {\\n\\t\\t\\terrorMessage\\n\\t\\t\\terrorCode\\n\\t\\t\\tpath\\n\\t\\t\\tproviderId\\n\\t\\t}\\n\\t\\t... on InvalidField {\\n\\t\\t\\terrorMessage\\n\\t\\t\\terrorCode\\n\\t\\t\\tfieldName\\n\\t\\t}\\n\\t}\\n}\\n\",\"operationName\":\"UpdateFieldMapping\"}"
         },
         "parameters":[
            
         ],
         "headers":[
            {
               "name":"Content-Type",
               "value":"application/json",
               "id":"pair_fccdc91d042c489f989a64df5c832664"
            },
            {
               "id":"pair_9174c34c090f451ca07b268a1a9d64ec",
               "name":"Authorization",
               "value":"{% response 'body', 'req_108b6d87926b4a1da95a1393d138ce93', 'b64::JC5BdXRoZW50aWNhdGlvblJlc3VsdC5JZFRva2Vu::46b', 'when-expired', 3000 %}",
               "description":""
            }
         ],
         "authentication":{
            
         },
         "metaSortKey":-1643623142535.125,
         "isPrivate":false,
         "settingStoreCookies":true,
         "settingSendCookies":true,
         "settingDisableRenderRequestBody":false,
         "settingEncodeUrl":true,
         "settingRebuildPath":true,
         "settingFollowRedirects":"global",
         "_type":"request"
      },
      {
         "_id":"req_6d9c2830b20d4f6ca88e1097d73f685f",
         "parentId":"wrk_4a5a7b0f3f1d40898c0652e42004d10c",
         "modified":1657573464900,
         "created":1652449263568,
         "url":"{{ _.graphql }}",
         "name":"Get field mappings",
         "description":"",
         "method":"POST",
         "body":{
            "mimeType":"application/graphql",
            "text":"{\"query\":\"query GetFieldMappings {\\n\\tgetFieldMappings(first: 10, providerId: \\\"{{ _.providerId }}\\\") {\\n\\t\\tedges {\\n\\t\\t\\tnode {\\n\\t\\t\\t\\tpath\\n\\t\\t\\t\\texpr\\n\\t\\t\\t}\\n\\t\\t}\\n\\t}\\n}\\n\",\"operationName\":\"GetFieldMappings\"}"
         },
         "parameters":[
            
         ],
         "headers":[
            {
               "name":"Content-Type",
               "value":"application/json",
               "id":"pair_fccdc91d042c489f989a64df5c832664"
            },
            {
               "id":"pair_9174c34c090f451ca07b268a1a9d64ec",
               "name":"Authorization",
               "value":"{% response 'body', 'req_108b6d87926b4a1da95a1393d138ce93', 'b64::JC5BdXRoZW50aWNhdGlvblJlc3VsdC5JZFRva2Vu::46b', 'when-expired', 3000 %}",
               "description":""
            }
         ],
         "authentication":{
            
         },
         "metaSortKey":-1643623142534.3438,
         "isPrivate":false,
         "settingStoreCookies":true,
         "settingSendCookies":true,
         "settingDisableRenderRequestBody":false,
         "settingEncodeUrl":true,
         "settingRebuildPath":true,
         "settingFollowRedirects":"global",
         "_type":"request"
      },
      {
         "_id":"req_68e7f1755e2d40e2aa1f7c566bec8683",
         "parentId":"wrk_4a5a7b0f3f1d40898c0652e42004d10c",
         "modified":1657573459564,
         "created":1652449229708,
         "url":"{{ _.graphql }}",
         "name":"Get deployed field mappings",
         "description":"",
         "method":"POST",
         "body":{
            "mimeType":"application/graphql",
            "text":"{\"query\":\"query GetDeployedFieldMappings {\\n\\tgetDeployedFieldMappings(first: 10, providerId: \\\"{{ _.providerId }}\\\") {\\n\\t\\tedges {\\n\\t\\t\\tnode {\\n\\t\\t\\t\\tproviderId\\n\\t\\t\\t\\tfrom\\n\\t\\t\\t\\tfieldMappings(first: 10) {\\n\\t\\t\\t\\t\\tedges {\\n\\t\\t\\t\\t\\t\\tnode {\\n\\t\\t\\t\\t\\t\\t\\tpath\\n\\t\\t\\t\\t\\t\\t\\texpr\\n\\t\\t\\t\\t\\t\\t}\\n\\t\\t\\t\\t\\t}\\n\\t\\t\\t\\t}\\n\\t\\t\\t}\\n\\t\\t}\\n\\t}\\n}\\n\",\"operationName\":\"GetDeployedFieldMappings\"}"
         },
         "parameters":[
            
         ],
         "headers":[
            {
               "name":"Content-Type",
               "value":"application/json",
               "id":"pair_fccdc91d042c489f989a64df5c832664"
            },
            {
               "id":"pair_9174c34c090f451ca07b268a1a9d64ec",
               "name":"Authorization",
               "value":"{% response 'body', 'req_108b6d87926b4a1da95a1393d138ce93', 'b64::JC5BdXRoZW50aWNhdGlvblJlc3VsdC5JZFRva2Vu::46b', 'when-expired', 3000 %}",
               "description":""
            }
         ],
         "authentication":{
            
         },
         "metaSortKey":-1643623142533.5625,
         "isPrivate":false,
         "settingStoreCookies":true,
         "settingSendCookies":true,
         "settingDisableRenderRequestBody":false,
         "settingEncodeUrl":true,
         "settingRebuildPath":true,
         "settingFollowRedirects":"global",
         "_type":"request"
      },
      {
         "_id":"env_16bf3a28001ced48399a2049d28e1b1adac132e2",
         "parentId":"wrk_4a5a7b0f3f1d40898c0652e42004d10c",
         "modified":1655925506300,
         "created":1643293092975,
         "name":"Base Environment",
         "data":{
            "elb":"REPLACE_ME",
            "cognito":"REPLACE_ME",
            "graphql":"REPLACE_ME",
            "diameter":"REPLACE_ME",
            "clientID":"REPLACE_ME"
         },
         "dataPropertyOrder":{
            "&":[
               "elb",
               "cognito",
               "graphql",
               "diameter",
               "clientID"
            ]
         },
         "color":null,
         "isPrivate":false,
         "metaSortKey":1643293092975,
         "_type":"environment"
      },
      {
         "_id":"jar_16bf3a28001ced48399a2049d28e1b1adac132e2",
         "parentId":"wrk_4a5a7b0f3f1d40898c0652e42004d10c",
         "modified":1643293092978,
         "created":1643293092978,
         "name":"Default Jar",
         "cookies":[
            
         ],
         "_type":"cookie_jar"
      },
      {
         "_id":"spc_66d570a0f5d74817b068bfadb51704f8",
         "parentId":"wrk_4a5a7b0f3f1d40898c0652e42004d10c",
         "modified":1643293092970,
         "created":1643293092970,
         "fileName":"Cloud Charging",
         "contents":"",
         "contentType":"yaml",
         "_type":"api_spec"
      },
      {
         "_id":"env_929da28685fa4674a0c71b363b7f0b20",
         "parentId":"env_16bf3a28001ced48399a2049d28e1b1adac132e2",
         "modified":1656964053421,
         "created":1656963821159,
         "name":"BlankEnvironment",
         "data":{
            "tenant_user_name":"youremail@domain.com",
            "tenant_password":"yourPassword",
            "config_user_name":"youremail@domain.com",
            "config_password":"yourPassword",
            "device_user_name":"youremail@domain.com",
            "device_password":"yourPassword",
            "infra_user_name":"youremail@domain.com",
            "infra_password":"yourPassword",
            "providerId":"abcdef12-345d-678e-90a1-234567bcdef8",
            "providerName":"rootca.yourcertificatedomain.com",
            "accountId":"accountId",
            "deviceId":"deviceId",
            "planName":"",
            "planId":"",
            "versionId":"",
            "elb":"REPLACE_ME",
            "cognito":"REPLACE_ME",
            "graphql":"REPLACE_ME",
            "diameter":"REPLACE_ME",
            "clientID":"REPLACE_ME"
         },
         "dataPropertyOrder":{
            "&":[
               "tenant_user_name",
               "tenant_password",
               "config_user_name",
               "config_password",
               "device_user_name",
               "device_password",
               "infra_user_name",
               "infra_password",
               "providerId",
               "providerName",
               "accountId",
               "deviceId",
               "planName",
               "planId",
               "versionId",
               "elb",
               "cognito",
               "graphql",
               "diameter",
               "clientID"
            ]
         },
         "color":null,
         "isPrivate":false,
         "metaSortKey":1655924897084.5,
         "_type":"environment"
      }
   ]
}